main.py
jam_inventory_managemnet_system-0.1.0.dist-info/METADATA
jam_inventory_managemnet_system-0.1.0.dist-info/WHEEL
jam_inventory_managemnet_system-0.1.0.dist-info/entry_points.txt
jam_inventory_managemnet_system-0.1.0.dist-info/top_level.txt
jam_inventory_managemnet_system-0.1.0.dist-info/RECORD
