Metadata-Version: 2.4
Name: jam-inventory-managemnet-system
Version: 0.1.0
Summary: A simple CLI inventory management system
Author-email: JamilaYDhedhi <nurjamila1@gmail.com>
Requires-Python: >=3.11
